board2048/__init__.py
board2048/board.py
board2048/board2048.py
board2048-1.0.1.dist-info/METADATA
board2048-1.0.1.dist-info/WHEEL
board2048-1.0.1.dist-info/top_level.txt
board2048-1.0.1.dist-info/zip-safe
board2048-1.0.1.dist-info/RECORD
